{
  "answers": [
    "A",
    "B"
  ],
  "options": [
    [
      "Waiting outside",
      "staying with Mrs White",
      "waiting at home",
      "helping the nurse"
    ],
    [
      "because the girl looked like him.",
      "Because his elder sister loved him.",
      "Because the girl looked like Mrs White.",
      "Because he didn't have much time to look after a boy."
    ]
  ],
  "questions": [
    "Mr White was  _   all the time.",
    "Why did Mr White like to have a girl?"
  ],
  "article": "Mrs White was going to have her first baby very soon. Yesterday her husband took her to a hospital.So Mr White helped her get into car and drove her there. A nurse  took Mrs White to her room and told Mr White that he could go home and she could call him when the baby arrived . But Mr White said he liked to wait at the hospital. The nurse said .\"You may wait outside.\" Mr White was walking up and down at about midnight when the nurse came out of the room and said with a smile.\"Which would you like better, a boy or a girl?\"\"A girl,\" said Mr White.\"I have an elder sister,and she loves me.\"\"Well,\"said the nurse,\"\"it's a boy this time.\"\"That's all right,\"said Mr White happily,\"That's my second choice.\"",
  "id": "asc19615"
}