{
  "answers": [
    "C",
    "D"
  ],
  "options": [
    [
      "give advice",
      "introduce new ways of body-building",
      "ask you to go to the center",
      "introduce ways to lose weight"
    ],
    [
      "the cheapest",
      "the largest",
      "the newest",
      "the most advanced"
    ]
  ],
  "questions": [
    "The purpose of this passage is to   _  .",
    "Through the advertisement, the center wants to show it's   _   one."
  ],
  "article": "With a busy life and job, pressure can make you look tired and aged.Kissi Health-Beauty Center gives classes, makes training plans according to your physical conditions, and sets up an individual file  .All these things will help you to get to know your body and the way to keep it fit.\n1)BODY-BUILDING\nImported   gym equipment that will help you build up your body's muscle, making you look full of energy and strength.\n2)GYMNASTIC EXERCISE\nA bright and large exercise room with excellent equipment and music will give your body a chance to enjoy movement with rhythm.\n3)SPECIAL \"LAZY-BONE\" FITNESS CENTER\n'Lazy-bone' fitness equipment is the first body shaping set of seven beds in Beijing, which helps you to exercise your waist, abdomen, hips or legs.In the relaxing hours you may try them to strengthen your muscles and lose weight.\n*Tuition: 'Lazy-bone' fitness card, 1,200 yuan/ month (gymnastic classes included)\n*Class Time: Gymnastic Class, 18:30-19:30 every Monday, Wednesday and Friday.\n*Tel: 5918570\n*Address: 16 Dongsanhuan Beilu, Chaoyang District, Beijing",
  "id": "asc10704"
}