{
  "answers": [
    "D",
    "C"
  ],
  "options": [
    [
      "Everything needs",
      "Everybody needs",
      "Nothing needs",
      "Everything and everybody need"
    ],
    [
      "water",
      "earth",
      "clouds",
      "lake"
    ]
  ],
  "questions": [
    "_   water.",
    "All water comes from   _  ."
  ],
  "article": "Everybody needs water. Everything needs water. We use water to wash the bowls , clothes and ourselves. We use water to plant trees, flowers and crops . Where does all water come from? It comes from clouds.\nSome of rain goes into the ground. Many people get it under the ground. Some rain water goes into the hills. It runs into lakes and rivers. Many people get it there.\n,.",
  "id": "asc24329"
}